LICENSE
MANIFEST.in
README.txt
setup.py
test.py
test.txt
Unlock.egg-info/PKG-INFO
Unlock.egg-info/SOURCES.txt
Unlock.egg-info/dependency_links.txt
Unlock.egg-info/requires.txt
Unlock.egg-info/top_level.txt
unlock/__init__.py
unlock/places.py
unlock/settings.py
unlock/test.txt
unlock/text.py