Metadata-Version: 1.0
Name: Unlock
Version: 0.15
Summary: Client for the Unlock web services
Home-page: http://unlock.edina.ac.uk/api.html
Author: Jo Walsh
Author-email: jo.walsh@ed.ac.uk
License: UNKNOWN
Platform: UNKNOWN
